sphinx_external_toc/__init__.py
sphinx_external_toc/_compat.py
sphinx_external_toc/api.py
sphinx_external_toc/cli.py
sphinx_external_toc/events.py
sphinx_external_toc/parsing.py
sphinx_external_toc/py.typed
sphinx_external_toc/tools.py
sphinx_external_toc-1.0.0.dist-info/entry_points.txt
sphinx_external_toc-1.0.0.dist-info/LICENSE
sphinx_external_toc-1.0.0.dist-info/WHEEL
sphinx_external_toc-1.0.0.dist-info/METADATA
sphinx_external_toc-1.0.0.dist-info/RECORD
