Metadata-Version: 2.1
Name: sphinx_external_toc
Version: 1.0.0
Summary: A sphinx extension that allows the site-map to be defined in a single YAML file.
Keywords: sphinx,extension,toc
Author-email: Chris Sewell <chrisj_sewell@hotmail.com>
Requires-Python: >=3.9
Classifier: Development Status :: 3 - Alpha
Classifier: Framework :: Sphinx :: Extension
Classifier: Intended Audience :: Developers
Classifier: License :: OSI Approved :: MIT License
Classifier: Programming Language :: Python :: 3
Classifier: Programming Language :: Python :: 3.9
Classifier: Programming Language :: Python :: 3.10
Classifier: Programming Language :: Python :: 3.11
Classifier: Programming Language :: Python :: 3.12
Classifier: Programming Language :: Python :: Implementation :: CPython
Classifier: Topic :: Software Development :: Libraries :: Python Modules
Classifier: Topic :: Text Processing :: Markup
Requires-Dist: click>=7.1
Requires-Dist: pyyaml
Requires-Dist: sphinx>=5
Requires-Dist: pre-commit>=2.12 ; extra == "code_style"
Requires-Dist: myst-parser>=1.0.0 ; extra == "rtd"
Requires-Dist: sphinx-book-theme>=1.0.0 ; extra == "rtd"
Requires-Dist: coverage ; extra == "testing"
Requires-Dist: pytest>=7.1 ; extra == "testing"
Requires-Dist: pytest-cov ; extra == "testing"
Requires-Dist: pytest-regressions ; extra == "testing"
Project-URL: Documentation, https://sphinx-external-toc.readthedocs.io
Project-URL: Homepage, https://github.com/executablebooks/sphinx-external-toc
Provides-Extra: code_style
Provides-Extra: rtd
Provides-Extra: testing
